cloudcraftz/__init__.py
cloudcraftz/finstats.py
cloudcraftz/new_optimizers.py
cloudcraftz/optimizers.py
cloudcraftz/plots.py
cloudcraftz/statistical_tests.py
cloudcraftz/technical_indicators.py
cloudcraftz/utils.py
cloudcraftz-1.4.7.dist-info/LICENSE.txt
cloudcraftz-1.4.7.dist-info/METADATA
cloudcraftz-1.4.7.dist-info/WHEEL
cloudcraftz-1.4.7.dist-info/top_level.txt
cloudcraftz-1.4.7.dist-info/RECORD
