Metadata-Version: 2.1
Name: cloudcraftz
Version: 1.4.7
Summary: Cloudcraftz: A Library for Financial Data Analysis and Pre-Processing.
Author: Neelakash Chatterjee
License: Cloudcraftz Solutions Pvt. Ltd. - www.cloudcraftz.com
License-File: LICENSE.txt
Requires-Dist: matplotlib (>=3.5.1)
Requires-Dist: numpy (>=1.21.0)
Requires-Dist: plotly (>=5.9.0)
Requires-Dist: pandas (>=1.3.4)
Requires-Dist: pykalman (>=0.9.5)
Requires-Dist: scipy (>=1.7.1)
Requires-Dist: seaborn (>=0.11.2)
Requires-Dist: empyrical (>=0.5.5)
Requires-Dist: openpyxl (>=3.0.10)
Requires-Dist: pymannkendall (>=1.4.2)
Requires-Dist: statsmodels (>=0.13.2)
Requires-Dist: yfinance
